{
  "$schema": "http://json-schema.org/draft-04/schema#",
  "id": "http://moj.gov.uk/cpp/results/domain/event/migrated-inactive-nces-email-notification-requested-exists.json",
  "type": "object",
  "properties": {
    "masterDefendantId": {
      "$ref": "http://justice.gov.uk/domain/core/common/definitions.json#/definitions/uuid"
    },
    "caseId": {
      "$ref": "http://justice.gov.uk/domain/core/common/definitions.json#/definitions/uuid"
    },
    "description": {
      "type": "string"
    }
  }
}