{
  "$schema":"http://json-schema.org/draft-04/schema#",
  "type":"object",
  "properties":{
    "hearingId":{
      "$ref":"#/definitions/uuidPattern"
    },
    "materialId":{
      "$ref":"#/definitions/uuidPattern"
    },
    "status":{
      "$ref":"#/definitions/status"
    }
  },
  "additionalProperties":false,
  "required":[
    "hearingId",
    "materialId",
    "status"
  ],
  "definitions":{
    "status":{
      "type":"string"
    },
    "uuidPattern":{
      "type":"string",
      "pattern":"^[a-fA-F0-9]{8}-[a-fA-F0-9]{4}-[a-fA-F0-9]{4}-[a-fA-F0-9]{4}-[a-fA-F0-9]{12}$"
    }
  }
}